{
  "title": "Games",
  "path": "_games",
  "page": 12,
  "value": [
    {
      "path": "_games/lowkotv-starcraft-2-domination-reynor-vs-heromarine-best-of-5.md",
      "title": "StarCraft 2: DOMINATION! Reynor vs HeRoMaRinE! (Best-of-5)",
      "excerpt": "Best-of-5 series of professional StarCraft 2. Zerg versus Terran series between Reynor and HeRoMaRinE.  Support my work on Patreon: http://www.patreon.com/lowkotv Become a YouTube member: https://lowko.tv/join  My second channel: http://lowko.tv/morelowko Lowko Merch: http://lowko.tv/merch  Be part of",
      "sourceUrl": "https://everyday-cc.github.io/starcraft2/api/games/lowkotv-starcraft-2-domination-reynor-vs-heromarine-best-of-5/index.json",
      "webUrl": "https://everyday.cc/starcraft2/game/lowkotv-starcraft-2-domination-reynor-vs-heromarine-best-of-5/",
      "originalUrl": "https://youtube.com/watch?v=O5v4_d3GxmY",
      "featuredContent": "<iframe width=\"800\" height=\"500\" frameborder=\"0\" src=\"https://www.youtube.com/embed/O5v4_d3GxmY\" allow=\"accelerometer; autoplay; encrypted-media; gyroscope; picture-in-picture\" allowfullscreen></iframe>",
      "length": "PT1H1M57S",
      "provider": {
        "name": "LowkoTV",
        "domain": "lowko.tv",
        "images": [
          {
            "url": "https://everyday-cc.github.io/starcraft2/assets/images/organizations/lowko.tv-50x50.jpg",
            "width": 50,
            "height": 50,
            "isCached": false
          }
        ]
      },
      "topics": [
        "StarCraft 2",
        "Zerg"
      ],
      "heat": 52,
      "images": [
        {
          "url": "https://i.ytimg.com/vi/O5v4_d3GxmY/maxresdefault.jpg",
          "width": 1280,
          "height": 720,
          "isCached": true
        }
      ],
      "content": "\r\n",
      "type": "video",
      "publishedDateTime": "2021-02-10T04:37:40-08:00"
    },
    {
      "path": "_games/lowkotv-starcraft-2-drgs-ravager-rush-at-300-minutes-vs-byun-best-of-5.md",
      "title": "StarCraft 2: DRG's RAVAGER RUSH at 3:00 Minutes vs ByuN! (Best-of-5)",
      "excerpt": "Best-of-5 series of professional StarCraft 2 between ByuN (Terran) and DRG (Zerg). Some solid macro games, and some cheesy matches and plenty of mistakes.  Support my work on Patreon: https://www.patreon.com/lowkotv Become a YouTube member: https://lowko.tv/join  More Lowko: https://youtube.com/morelowko",
      "sourceUrl": "https://everyday-cc.github.io/starcraft2/api/games/lowkotv-starcraft-2-drgs-ravager-rush-at-300-minutes-vs-byun-best-of-5/index.json",
      "webUrl": "https://everyday.cc/starcraft2/game/lowkotv-starcraft-2-drgs-ravager-rush-at-300-minutes-vs-byun-best-of-5/",
      "originalUrl": "https://youtube.com/watch?v=bCPZpjETRRo",
      "featuredContent": "<iframe width=\"800\" height=\"500\" frameborder=\"0\" src=\"https://www.youtube.com/embed/bCPZpjETRRo\" allow=\"accelerometer; autoplay; encrypted-media; gyroscope; picture-in-picture\" allowfullscreen></iframe>",
      "length": "PT48M24S",
      "provider": {
        "name": "LowkoTV",
        "domain": "lowko.tv",
        "images": [
          {
            "url": "https://everyday-cc.github.io/starcraft2/assets/images/organizations/lowko.tv-50x50.jpg",
            "width": 50,
            "height": 50,
            "isCached": false
          }
        ]
      },
      "topics": [
        "StarCraft 2",
        "Terran"
      ],
      "heat": 52,
      "images": [
        {
          "url": "https://www.youtube.com/img/desktop/supported_browsers/dinosaur.png",
          "width": 1200,
          "height": 800,
          "isCached": true
        }
      ],
      "content": "\r\n",
      "type": "video",
      "publishedDateTime": "2022-04-05T03:02:33-07:00"
    },
    {
      "path": "_games/lowkotv-starcraft-2-empty-medivac-aggression-byun-vs-zest.md",
      "title": "StarCraft 2: EMPTY Medivac Aggression?! (ByuN vs Zest)",
      "excerpt": "Best-of-5 series of professional StarCraft 2 between ByuN (Terran) and Zest (Protoss).  TLMC 16 Map Contest: https://youtu.be/Od0SQYvNdJU  Support my work on Patreon: https://www.patreon.com/lowkotv Become a YouTube member: https://lowko.tv/join  More Lowko: https://youtube.com/morelowko Lowko Clips:",
      "sourceUrl": "https://everyday-cc.github.io/starcraft2/api/games/lowkotv-starcraft-2-empty-medivac-aggression-byun-vs-zest/index.json",
      "webUrl": "https://everyday.cc/starcraft2/game/lowkotv-starcraft-2-empty-medivac-aggression-byun-vs-zest/",
      "originalUrl": "https://youtube.com/watch?v=M2317u4k2Gc",
      "featuredContent": "<iframe width=\"800\" height=\"500\" frameborder=\"0\" src=\"https://www.youtube.com/embed/M2317u4k2Gc\" allow=\"accelerometer; autoplay; encrypted-media; gyroscope; picture-in-picture\" allowfullscreen></iframe>",
      "length": "PT54M14S",
      "provider": {
        "name": "LowkoTV",
        "domain": "lowko.tv",
        "images": [
          {
            "url": "https://everyday-cc.github.io/starcraft2/assets/images/organizations/lowko.tv-50x50.jpg",
            "width": 50,
            "height": 50,
            "isCached": false
          }
        ]
      },
      "topics": [
        "StarCraft 2",
        "Terran",
        "Protoss"
      ],
      "heat": 52,
      "images": [
        {
          "url": "https://i.ytimg.com/vi/M2317u4k2Gc/maxresdefault.jpg",
          "width": 1280,
          "height": 720,
          "isCached": true
        }
      ],
      "content": "\r\n",
      "type": "video",
      "publishedDateTime": "2022-02-07T11:02:25-08:00"
    },
    {
      "path": "_games/lowkotv-starcraft-2-epic-match-reinventing-terran-mech.md",
      "title": "StarCraft 2: Epic Match!  REINVENTING TERRAN MECH?!",
      "excerpt": "A really good best-of-5 series between Dark and Gumiho. Subscribe for more videos: http://lowko.tv/youtube Drone rush vs Drone rush: https://goo.gl/GsDVVk  Easily one of the best best-of-5 series of Zerg vs Terran I've seen in recent times. It looks like Gumhio is reinventing Terran Mech. Super cool",
      "sourceUrl": "https://everyday-cc.github.io/starcraft2/api/games/lowkotv-starcraft-2-epic-match-reinventing-terran-mech/index.json",
      "webUrl": "https://everyday.cc/starcraft2/game/lowkotv-starcraft-2-epic-match-reinventing-terran-mech/",
      "originalUrl": "https://youtube.com/watch?v=mf5jx5TOnR4",
      "featuredContent": "<iframe width=\"800\" height=\"500\" frameborder=\"0\" src=\"https://www.youtube.com/embed/mf5jx5TOnR4\" allow=\"accelerometer; autoplay; encrypted-media; gyroscope; picture-in-picture\" allowfullscreen></iframe>",
      "length": "PT1H12M51S",
      "provider": {
        "name": "LowkoTV",
        "domain": "lowko.tv",
        "images": [
          {
            "url": "https://everyday-cc.github.io/starcraft2/assets/images/organizations/lowko.tv-50x50.jpg",
            "width": 50,
            "height": 50,
            "isCached": false
          }
        ]
      },
      "topics": [
        "StarCraft 2",
        "Terran"
      ],
      "heat": 52,
      "images": [
        {
          "url": "https://i.ytimg.com/vi/mf5jx5TOnR4/maxresdefault.jpg",
          "width": 1280,
          "height": 720,
          "isCached": true
        }
      ],
      "content": "\r\n",
      "type": "video",
      "publishedDateTime": "2018-10-24T02:02:31-07:00"
    },
    {
      "path": "_games/lowkotv-starcraft-2-epic-pro-level-2v2-maru-sos-vs-prince-drgling.md",
      "title": "StarCraft 2: EPIC PRO LEVEL 2v2 - Maru & sOs vs Prince & DRGLing!",
      "excerpt": "Maru and sOs versus Prince and DRGLing in an epic game of 2v2 in StarCraft 2.  OlimoLeague on Patreon: https://www.patreon.com/olimoley  More professional 2v2: https://youtu.be/qk3OKS90ckA StarCraft 2 Free For All: https://youtu.be/hmLp9wr8ASo  Support my work on Patreon: http://www.patreon.com/lowkotv",
      "sourceUrl": "https://everyday-cc.github.io/starcraft2/api/games/lowkotv-starcraft-2-epic-pro-level-2v2-maru-sos-vs-prince-drgling/index.json",
      "webUrl": "https://everyday.cc/starcraft2/game/lowkotv-starcraft-2-epic-pro-level-2v2-maru-sos-vs-prince-drgling/",
      "originalUrl": "https://youtube.com/watch?v=VeUii-Dm4ps",
      "featuredContent": "<iframe width=\"800\" height=\"500\" frameborder=\"0\" src=\"https://www.youtube.com/embed/VeUii-Dm4ps\" allow=\"accelerometer; autoplay; encrypted-media; gyroscope; picture-in-picture\" allowfullscreen></iframe>",
      "length": "PT30M54S",
      "provider": {
        "name": "LowkoTV",
        "domain": "lowko.tv",
        "images": [
          {
            "url": "https://everyday-cc.github.io/starcraft2/assets/images/organizations/lowko.tv-50x50.jpg",
            "width": 50,
            "height": 50,
            "isCached": false
          }
        ]
      },
      "topics": [
        "StarCraft 2",
        "Terran",
        "Protoss"
      ],
      "heat": 52,
      "images": [
        {
          "url": "https://i.ytimg.com/vi/VeUii-Dm4ps/maxresdefault.jpg",
          "width": 1280,
          "height": 720,
          "isCached": true
        }
      ],
      "content": "\r\n",
      "type": "video",
      "publishedDateTime": "2021-08-10T03:20:57-07:00"
    },
    {
      "path": "_games/lowkotv-starcraft-2-extreme-dark-templar-zealot-runbys-best-of-5.md",
      "title": "StarCraft 2: EXTREME Dark Templar & Zealot Runbys! (Best-of-5)",
      "excerpt": "Best-of-5 series of professional StarCraft 2 between Zest (Protoss) and Cure (Terran).  Support my work on Patreon: https://www.patreon.com/lowkotv Become a YouTube member: https://lowko.tv/join  My second channel: https://youtube.com/morelowko Lowko Merch: http://lowko.tv/merch  Be part of the community",
      "sourceUrl": "https://everyday-cc.github.io/starcraft2/api/games/lowkotv-starcraft-2-extreme-dark-templar-zealot-runbys-best-of-5/index.json",
      "webUrl": "https://everyday.cc/starcraft2/game/lowkotv-starcraft-2-extreme-dark-templar-zealot-runbys-best-of-5/",
      "originalUrl": "https://youtube.com/watch?v=Bep8cI3u2zM",
      "featuredContent": "<iframe width=\"800\" height=\"500\" frameborder=\"0\" src=\"https://www.youtube.com/embed/Bep8cI3u2zM\" allow=\"accelerometer; autoplay; encrypted-media; gyroscope; picture-in-picture\" allowfullscreen></iframe>",
      "length": "PT59M25S",
      "provider": {
        "name": "LowkoTV",
        "domain": "lowko.tv",
        "images": [
          {
            "url": "https://everyday-cc.github.io/starcraft2/assets/images/organizations/lowko.tv-50x50.jpg",
            "width": 50,
            "height": 50,
            "isCached": false
          }
        ]
      },
      "topics": [
        "StarCraft 2",
        "Zerg"
      ],
      "heat": 52,
      "images": [
        {
          "url": "https://i.ytimg.com/vi/Bep8cI3u2zM/maxresdefault.jpg",
          "width": 1280,
          "height": 720,
          "isCached": true
        }
      ],
      "content": "\r\n",
      "type": "video",
      "publishedDateTime": "2022-01-22T04:58:16-08:00"
    },
    {
      "path": "_games/lowkotv-starcraft-2-fastest-grand-finals-ever-dark-vs-byun.md",
      "title": "StarCraft 2: Fastest GRAND FINALS Ever? (Dark vs ByuN)",
      "excerpt": "The Grand Finals of the ESL Open Cup 124 Korea. In this best-of-5 series of professional StarCraft 2 I cast ByuN (Terran) versus Dark (Zerg). Easily one of the fastest Grand Finals ever in StarCraft 2. The fastest StarCraft 2 speedrun?  Support my work on Patreon: https://www.patreon.com/lowkotv Become",
      "sourceUrl": "https://everyday-cc.github.io/starcraft2/api/games/lowkotv-starcraft-2-fastest-grand-finals-ever-dark-vs-byun/index.json",
      "webUrl": "https://everyday.cc/starcraft2/game/lowkotv-starcraft-2-fastest-grand-finals-ever-dark-vs-byun/",
      "originalUrl": "https://youtube.com/watch?v=Wgl-beRNXKM",
      "featuredContent": "<iframe width=\"800\" height=\"500\" frameborder=\"0\" src=\"https://www.youtube.com/embed/Wgl-beRNXKM\" allow=\"accelerometer; autoplay; encrypted-media; gyroscope; picture-in-picture\" allowfullscreen></iframe>",
      "length": "PT13M32S",
      "provider": {
        "name": "LowkoTV",
        "domain": "lowko.tv",
        "images": [
          {
            "url": "https://everyday-cc.github.io/starcraft2/assets/images/organizations/lowko.tv-50x50.jpg",
            "width": 50,
            "height": 50,
            "isCached": false
          }
        ]
      },
      "topics": [
        "StarCraft 2",
        "Terran",
        "Zerg"
      ],
      "heat": 52,
      "images": [
        {
          "url": "https://www.youtube.com/img/desktop/supported_browsers/dinosaur.png",
          "width": 1200,
          "height": 800,
          "isCached": true
        }
      ],
      "content": "\r\n",
      "type": "video",
      "publishedDateTime": "2022-05-24T01:14:41-07:00"
    },
    {
      "path": "_games/lowkotv-starcraft-2-florencio-gets-rushed.md",
      "title": "StarCraft 2: FLORENCIO Gets Rushed!",
      "excerpt": "A game of Zerg versus Protoss in StarCraft 2 with some very creative strategies.  Support my work on Patreon: http://www.patreon.com/lowkotv Become a YouTube member: https://lowko.tv/join  My second channel: http://lowko.tv/morelowko Lowko Merch: http://lowko.tv/merch  Be part of the community on Discord:",
      "sourceUrl": "https://everyday-cc.github.io/starcraft2/api/games/lowkotv-starcraft-2-florencio-gets-rushed/index.json",
      "webUrl": "https://everyday.cc/starcraft2/game/lowkotv-starcraft-2-florencio-gets-rushed/",
      "originalUrl": "https://youtube.com/watch?v=nB24pHjh_eI",
      "featuredContent": "<iframe width=\"800\" height=\"500\" frameborder=\"0\" src=\"https://www.youtube.com/embed/nB24pHjh_eI\" allow=\"accelerometer; autoplay; encrypted-media; gyroscope; picture-in-picture\" allowfullscreen></iframe>",
      "length": "PT31M18S",
      "provider": {
        "name": "LowkoTV",
        "domain": "lowko.tv",
        "images": [
          {
            "url": "https://everyday-cc.github.io/starcraft2/assets/images/organizations/lowko.tv-50x50.jpg",
            "width": 50,
            "height": 50,
            "isCached": false
          }
        ]
      },
      "topics": [
        "StarCraft 2"
      ],
      "heat": 52,
      "images": [
        {
          "url": "https://i.ytimg.com/vi/nB24pHjh_eI/maxresdefault.jpg",
          "width": 1280,
          "height": 720,
          "isCached": true
        }
      ],
      "content": "\r\n",
      "type": "video",
      "publishedDateTime": "2021-09-23T04:41:23-07:00"
    },
    {
      "path": "_games/lowkotv-starcraft-2-florencio-is-feeling-gouda.md",
      "title": "StarCraft 2: FLORENCIO Is Feeling Gouda!",
      "excerpt": "Florencio is back with other crazy strategies in StarCraft 2. Hiding Starport production with a lifting Factory. Landed Vikings inside of Medivacs. Massing Thors and Tactical Nukes. And a whole lot more.  Support my work on Patreon: http://www.patreon.com/lowkotv Become a YouTube member: https://lowko.tv/join",
      "sourceUrl": "https://everyday-cc.github.io/starcraft2/api/games/lowkotv-starcraft-2-florencio-is-feeling-gouda/index.json",
      "webUrl": "https://everyday.cc/starcraft2/game/lowkotv-starcraft-2-florencio-is-feeling-gouda/",
      "originalUrl": "https://youtube.com/watch?v=AGZZFwqTjBg",
      "featuredContent": "<iframe width=\"800\" height=\"500\" frameborder=\"0\" src=\"https://www.youtube.com/embed/AGZZFwqTjBg\" allow=\"accelerometer; autoplay; encrypted-media; gyroscope; picture-in-picture\" allowfullscreen></iframe>",
      "length": "PT44M6S",
      "provider": {
        "name": "LowkoTV",
        "domain": "lowko.tv",
        "images": [
          {
            "url": "https://everyday-cc.github.io/starcraft2/assets/images/organizations/lowko.tv-50x50.jpg",
            "width": 50,
            "height": 50,
            "isCached": false
          }
        ]
      },
      "topics": [
        "StarCraft 2"
      ],
      "heat": 52,
      "images": [
        {
          "url": "https://i.ytimg.com/vi/AGZZFwqTjBg/maxresdefault.jpg",
          "width": 1280,
          "height": 720,
          "isCached": true
        }
      ],
      "content": "\r\n",
      "type": "video",
      "publishedDateTime": "2021-05-04T04:18:24-07:00"
    },
    {
      "path": "_games/lowkotv-starcraft-2-florencios-scv-rush.md",
      "title": "StarCraft 2: FLORENCIO'S SCV RUSH!",
      "excerpt": "A fun match of Terran versus Protoss in StarCraft 2 submitted by the legend Florencio. In this match he decides to go for a worker rush as Terran versus an unsuspecting Protoss, while at the same time also flying his Command Center off to the island base on the map Purity and Industry.  Tactical Nukes",
      "sourceUrl": "https://everyday-cc.github.io/starcraft2/api/games/lowkotv-starcraft-2-florencios-scv-rush/index.json",
      "webUrl": "https://everyday.cc/starcraft2/game/lowkotv-starcraft-2-florencios-scv-rush/",
      "originalUrl": "https://youtube.com/watch?v=MN1rcDkgbrg",
      "featuredContent": "<iframe width=\"800\" height=\"500\" frameborder=\"0\" src=\"https://www.youtube.com/embed/MN1rcDkgbrg\" allow=\"accelerometer; autoplay; encrypted-media; gyroscope; picture-in-picture\" allowfullscreen></iframe>",
      "length": "PT15M26S",
      "provider": {
        "name": "LowkoTV",
        "domain": "lowko.tv",
        "images": [
          {
            "url": "https://everyday-cc.github.io/starcraft2/assets/images/organizations/lowko.tv-50x50.jpg",
            "width": 50,
            "height": 50,
            "isCached": false
          }
        ]
      },
      "topics": [
        "StarCraft 2"
      ],
      "heat": 52,
      "images": [
        {
          "url": "https://i.ytimg.com/vi/MN1rcDkgbrg/maxresdefault.jpg",
          "width": 1280,
          "height": 720,
          "isCached": true
        }
      ],
      "content": "\r\n",
      "type": "video",
      "publishedDateTime": "2020-05-08T03:20:19-07:00"
    },
    {
      "path": "_games/lowkotv-starcraft-2-fun-game-specials-battlecruiser-rush-vs-byun.md",
      "title": "StarCraft 2: FUN GAME - SpeCial's Battlecruiser Rush vs ByuN!",
      "excerpt": "Awesome game of professional StarCraft 2 between SpeCial (Terran) versus ByuN (Terran). In this game SpeCial decides to go for a Battlecruiser Proxy and transitions towards Terran Mech. ByuN instead goes for the standard approach of Marines and Siege Tanks.  Support my work on Patreon: https://www.patreon.com/lowkotv",
      "sourceUrl": "https://everyday-cc.github.io/starcraft2/api/games/lowkotv-starcraft-2-fun-game-specials-battlecruiser-rush-vs-byun/index.json",
      "webUrl": "https://everyday.cc/starcraft2/game/lowkotv-starcraft-2-fun-game-specials-battlecruiser-rush-vs-byun/",
      "originalUrl": "https://youtube.com/watch?v=eghsu3vyQjc",
      "featuredContent": "<iframe width=\"800\" height=\"500\" frameborder=\"0\" src=\"https://www.youtube.com/embed/eghsu3vyQjc\" allow=\"accelerometer; autoplay; encrypted-media; gyroscope; picture-in-picture\" allowfullscreen></iframe>",
      "length": "PT26M7S",
      "provider": {
        "name": "LowkoTV",
        "domain": "lowko.tv",
        "images": [
          {
            "url": "https://everyday-cc.github.io/starcraft2/assets/images/organizations/lowko.tv-50x50.jpg",
            "width": 50,
            "height": 50,
            "isCached": false
          }
        ]
      },
      "topics": [
        "StarCraft 2",
        "Terran"
      ],
      "heat": 52,
      "images": [
        {
          "url": "https://www.youtube.com/img/desktop/supported_browsers/dinosaur.png",
          "width": 1200,
          "height": 800,
          "isCached": true
        }
      ],
      "content": "\r\n",
      "type": "video",
      "publishedDateTime": "2022-07-12T02:06:32-07:00"
    },
    {
      "path": "_games/lowkotv-starcraft-2-hero-loves-phoenix-builds-drg-vs-hero.md",
      "title": "StarCraft 2: herO LOVES Phoenix Builds! (DRG vs herO)",
      "excerpt": "Best-of-5 series of professional StarCraft 2 between DRG (Zerg) and herO (Protoss). Turns out Phoenix openers are pretty good.  Support my work on Patreon: https://www.patreon.com/lowkotv Become a YouTube member: https://lowko.tv/join  More Lowko: https://youtube.com/morelowko Lowko Clips: https://www.youtube.com/lowkoclips",
      "sourceUrl": "https://everyday-cc.github.io/starcraft2/api/games/lowkotv-starcraft-2-hero-loves-phoenix-builds-drg-vs-hero/index.json",
      "webUrl": "https://everyday.cc/starcraft2/game/lowkotv-starcraft-2-hero-loves-phoenix-builds-drg-vs-hero/",
      "originalUrl": "https://youtube.com/watch?v=fMUxiGztMYs",
      "featuredContent": "<iframe width=\"800\" height=\"500\" frameborder=\"0\" src=\"https://www.youtube.com/embed/fMUxiGztMYs\" allow=\"accelerometer; autoplay; encrypted-media; gyroscope; picture-in-picture\" allowfullscreen></iframe>",
      "length": "PT54M43S",
      "provider": {
        "name": "LowkoTV",
        "domain": "lowko.tv",
        "images": [
          {
            "url": "https://everyday-cc.github.io/starcraft2/assets/images/organizations/lowko.tv-50x50.jpg",
            "width": 50,
            "height": 50,
            "isCached": false
          }
        ]
      },
      "topics": [
        "StarCraft 2",
        "Protoss"
      ],
      "heat": 52,
      "images": [
        {
          "url": "https://www.youtube.com/img/desktop/supported_browsers/dinosaur.png",
          "width": 1200,
          "height": 800,
          "isCached": true
        }
      ],
      "content": "\r\n",
      "type": "video",
      "publishedDateTime": "2022-04-02T04:56:13-07:00"
    },
    {
      "path": "_games/lowkotv-starcraft-2-lowko-complains-about-zests-mass-void-ray-vs-soo-best-of-5.md",
      "title": "StarCraft 2; Lowko Complains About Zest’s MASS VOID RAY vs soO! (Best-of-5)",
      "excerpt": "Best-of-5 series of professional StarCraft 2 between soO (Zerg) and Zest (Protoss). After macro games soO decides to go for a Spine Crawler rush versus Zest.  soO vs Cure: https://youtu.be/EfILZ7FPv70 soO vs ByuN: https://youtu.be/mSL43Z7w6A4  Support my work on Patreon: https://www.patreon.com/lowkotv",
      "sourceUrl": "https://everyday-cc.github.io/starcraft2/api/games/lowkotv-starcraft-2-lowko-complains-about-zests-mass-void-ray-vs-soo-best-of-5/index.json",
      "webUrl": "https://everyday.cc/starcraft2/game/lowkotv-starcraft-2-lowko-complains-about-zests-mass-void-ray-vs-soo-best-of-5/",
      "originalUrl": "https://youtube.com/watch?v=nQJJ-2RhILc",
      "featuredContent": "<iframe width=\"800\" height=\"500\" frameborder=\"0\" src=\"https://www.youtube.com/embed/nQJJ-2RhILc\" allow=\"accelerometer; autoplay; encrypted-media; gyroscope; picture-in-picture\" allowfullscreen></iframe>",
      "length": "PT44M50S",
      "provider": {
        "name": "LowkoTV",
        "domain": "lowko.tv",
        "images": [
          {
            "url": "https://everyday-cc.github.io/starcraft2/assets/images/organizations/lowko.tv-50x50.jpg",
            "width": 50,
            "height": 50,
            "isCached": false
          }
        ]
      },
      "topics": [
        "StarCraft 2",
        "Protoss",
        "Zerg"
      ],
      "heat": 52,
      "images": [
        {
          "url": "https://www.youtube.com/img/desktop/supported_browsers/dinosaur.png",
          "width": 1200,
          "height": 800,
          "isCached": true
        }
      ],
      "content": "\r\n",
      "type": "video",
      "publishedDateTime": "2022-05-23T11:16:38-07:00"
    },
    {
      "path": "_games/lowkotv-starcraft-2-maru-vs-serral-best-of-5.md",
      "title": "StarCraft 2: MARU vs SERRAL! (Best-of-5)",
      "excerpt": "In this best-of-5 series of professional StarCraft 2 we watch Serral face off against Maru in a Zerg versus Terran. This is the best player from South Korea, going up against the best player outside of South Korea.  Serral vs Trap Grand Finals (Dreamhack Fall): https://youtu.be/Bxi7syqMyXI  Support my",
      "sourceUrl": "https://everyday-cc.github.io/starcraft2/api/games/lowkotv-starcraft-2-maru-vs-serral-best-of-5/index.json",
      "webUrl": "https://everyday.cc/starcraft2/game/lowkotv-starcraft-2-maru-vs-serral-best-of-5/",
      "originalUrl": "https://youtube.com/watch?v=bDK8Ps8UAOE",
      "featuredContent": "<iframe width=\"800\" height=\"500\" frameborder=\"0\" src=\"https://www.youtube.com/embed/bDK8Ps8UAOE\" allow=\"accelerometer; autoplay; encrypted-media; gyroscope; picture-in-picture\" allowfullscreen></iframe>",
      "length": "PT51M40S",
      "provider": {
        "name": "LowkoTV",
        "domain": "lowko.tv",
        "images": [
          {
            "url": "https://everyday-cc.github.io/starcraft2/assets/images/organizations/lowko.tv-50x50.jpg",
            "width": 50,
            "height": 50,
            "isCached": false
          }
        ]
      },
      "topics": [
        "StarCraft 2",
        "Terran",
        "Zerg"
      ],
      "heat": 52,
      "images": [
        {
          "url": "https://i.ytimg.com/vi/bDK8Ps8UAOE/maxresdefault.jpg",
          "width": 1280,
          "height": 720,
          "isCached": true
        }
      ],
      "content": "\r\n",
      "type": "video",
      "publishedDateTime": "2021-09-21T04:19:21-07:00"
    },
    {
      "path": "_games/lowkotv-starcraft-2-marus-massive-tactical-nuke-vs-solar-best-of-3.md",
      "title": "StarCraft 2: Maru's MASSIVE Tactical Nuke vs Solar! (Best-of-3)",
      "excerpt": "Best-of-3 series of professional StarCraft 2 between Maru and Solar. Easily of the biggest Nukes in a professional match of SC2 ever.  Support my work on Patreon: http://www.patreon.com/lowkotv Become a YouTube member: https://lowko.tv/join  My second channel: http://lowko.tv/morelowko Lowko Merch: http://lowko.tv/merch",
      "sourceUrl": "https://everyday-cc.github.io/starcraft2/api/games/lowkotv-starcraft-2-marus-massive-tactical-nuke-vs-solar-best-of-3/index.json",
      "webUrl": "https://everyday.cc/starcraft2/game/lowkotv-starcraft-2-marus-massive-tactical-nuke-vs-solar-best-of-3/",
      "originalUrl": "https://youtube.com/watch?v=LNKvSjzZXr8",
      "featuredContent": "<iframe width=\"800\" height=\"500\" frameborder=\"0\" src=\"https://www.youtube.com/embed/LNKvSjzZXr8\" allow=\"accelerometer; autoplay; encrypted-media; gyroscope; picture-in-picture\" allowfullscreen></iframe>",
      "length": "PT49M37S",
      "provider": {
        "name": "LowkoTV",
        "domain": "lowko.tv",
        "images": [
          {
            "url": "https://everyday-cc.github.io/starcraft2/assets/images/organizations/lowko.tv-50x50.jpg",
            "width": 50,
            "height": 50,
            "isCached": false
          }
        ]
      },
      "topics": [
        "StarCraft 2",
        "Terran",
        "Zerg"
      ],
      "heat": 52,
      "images": [
        {
          "url": "https://i.ytimg.com/vi/LNKvSjzZXr8/maxresdefault.jpg",
          "width": 1280,
          "height": 720,
          "isCached": true
        }
      ],
      "content": "\r\n",
      "type": "video",
      "publishedDateTime": "2021-03-04T04:51:27-08:00"
    },
    {
      "path": "_games/lowkotv-starcraft-2-mass-siege-tank-vs-protoss.md",
      "title": "StarCraft 2: Mass Siege Tank vs Protoss!",
      "excerpt": "A best-of-5 series of professional StarCraft 2 between uThermal and Harstem, the two best pro gamers from the Netherlands.  Get more videos & support my work: http://www.patreon.com/lowkotv  Be part of the community on Discord: http://discord.gg/lowkotv The hardware setup I use: https://lowko.tv/setup/",
      "sourceUrl": "https://everyday-cc.github.io/starcraft2/api/games/lowkotv-starcraft-2-mass-siege-tank-vs-protoss/index.json",
      "webUrl": "https://everyday.cc/starcraft2/game/lowkotv-starcraft-2-mass-siege-tank-vs-protoss/",
      "originalUrl": "https://youtube.com/watch?v=iXO2XbL7ESE",
      "featuredContent": "<iframe width=\"800\" height=\"500\" frameborder=\"0\" src=\"https://www.youtube.com/embed/iXO2XbL7ESE\" allow=\"accelerometer; autoplay; encrypted-media; gyroscope; picture-in-picture\" allowfullscreen></iframe>",
      "length": "PT52M24S",
      "provider": {
        "name": "LowkoTV",
        "domain": "lowko.tv",
        "images": [
          {
            "url": "https://everyday-cc.github.io/starcraft2/assets/images/organizations/lowko.tv-50x50.jpg",
            "width": 50,
            "height": 50,
            "isCached": false
          }
        ]
      },
      "topics": [
        "StarCraft 2",
        "Terran",
        "Protoss"
      ],
      "heat": 52,
      "images": [
        {
          "url": "https://i.ytimg.com/vi/iXO2XbL7ESE/maxresdefault.jpg",
          "width": 1280,
          "height": 720,
          "isCached": true
        }
      ],
      "content": "\r\n",
      "type": "video",
      "publishedDateTime": "2019-09-03T03:51:47-07:00"
    },
    {
      "path": "_games/lowkotv-starcraft-2-maxpaxs-incredible-stargate-proxies.md",
      "title": "StarCraft 2: MaxPax's Incredible Stargate PROXIES!",
      "excerpt": "Best-of-5 series of professional StarCraft 2 between MaxPax and soul. MaxPax has been playing some awesome SC2 with a variety of build orders and strategies.  Support my work on Patreon: http://www.patreon.com/lowkotv Become a YouTube member: https://lowko.tv/join  My second channel: http://lowko.tv/morelowko",
      "sourceUrl": "https://everyday-cc.github.io/starcraft2/api/games/lowkotv-starcraft-2-maxpaxs-incredible-stargate-proxies/index.json",
      "webUrl": "https://everyday.cc/starcraft2/game/lowkotv-starcraft-2-maxpaxs-incredible-stargate-proxies/",
      "originalUrl": "https://youtube.com/watch?v=TT64gcEXKZA",
      "featuredContent": "<iframe width=\"800\" height=\"500\" frameborder=\"0\" src=\"https://www.youtube.com/embed/TT64gcEXKZA\" allow=\"accelerometer; autoplay; encrypted-media; gyroscope; picture-in-picture\" allowfullscreen></iframe>",
      "length": "PT56M28S",
      "provider": {
        "name": "LowkoTV",
        "domain": "lowko.tv",
        "images": [
          {
            "url": "https://everyday-cc.github.io/starcraft2/assets/images/organizations/lowko.tv-50x50.jpg",
            "width": 50,
            "height": 50,
            "isCached": false
          }
        ]
      },
      "topics": [
        "StarCraft 2"
      ],
      "heat": 52,
      "images": [
        {
          "url": "https://i.ytimg.com/vi/TT64gcEXKZA/maxresdefault.jpg",
          "width": 1280,
          "height": 720,
          "isCached": true
        }
      ],
      "content": "\r\n",
      "type": "video",
      "publishedDateTime": "2021-02-02T04:37:11-08:00"
    },
    {
      "path": "_games/lowkotv-starcraft-2-micro-wars-byun-and-hero-cant-stop-fighting.md",
      "title": "StarCraft 2: MICRO WARS - ByuN and herO can't stop fighting!",
      "excerpt": "Great game of StarCraft 2 between ByuN and herO. In this Terran versus Protoss on Waterfall, one of the new maps, we watch two pro gamers face off in non-stop aggression.  Rogue vs herO: https://youtu.be/rqFbx1bdKgA ByuN vs Creator: https://youtu.be/TNrl1eXuAdg  Support my work on Patreon: https://www.patreon.com/lowkotv",
      "sourceUrl": "https://everyday-cc.github.io/starcraft2/api/games/lowkotv-starcraft-2-micro-wars-byun-and-hero-cant-stop-fighting/index.json",
      "webUrl": "https://everyday.cc/starcraft2/game/lowkotv-starcraft-2-micro-wars-byun-and-hero-cant-stop-fighting/",
      "originalUrl": "https://youtube.com/watch?v=KaIjDJ3FNeI",
      "featuredContent": "<iframe width=\"800\" height=\"500\" frameborder=\"0\" src=\"https://www.youtube.com/embed/KaIjDJ3FNeI\" allow=\"accelerometer; autoplay; encrypted-media; gyroscope; picture-in-picture\" allowfullscreen></iframe>",
      "length": "PT28M47S",
      "provider": {
        "name": "LowkoTV",
        "domain": "lowko.tv",
        "images": [
          {
            "url": "https://everyday-cc.github.io/starcraft2/assets/images/organizations/lowko.tv-50x50.jpg",
            "width": 50,
            "height": 50,
            "isCached": false
          }
        ]
      },
      "topics": [
        "StarCraft 2",
        "Terran",
        "Protoss"
      ],
      "heat": 52,
      "images": [
        {
          "url": "https://www.youtube.com/img/desktop/supported_browsers/dinosaur.png",
          "width": 1200,
          "height": 800,
          "isCached": true
        }
      ],
      "content": "\r\n",
      "type": "video",
      "publishedDateTime": "2022-07-01T04:15:55-07:00"
    },
    {
      "path": "_games/lowkotv-starcraft-2-mistakes-were-made-bly-vs-beastyqt.md",
      "title": "StarCraft 2: MISTAKES WERE MADE... (Bly vs BeastyQT)",
      "excerpt": "Fun game of StarCraft 2 between Bly and BeastyQT. Mistakes are made on both sides and because of that the game goes on until the map is almost entirely mined out.  Bly's YouTube channel: https://youtube.com/blyonfire Beasty's YouTube channel: https://youtube.com/beastyqtsc2   Become a YouTube member:",
      "sourceUrl": "https://everyday-cc.github.io/starcraft2/api/games/lowkotv-starcraft-2-mistakes-were-made-bly-vs-beastyqt/index.json",
      "webUrl": "https://everyday.cc/starcraft2/game/lowkotv-starcraft-2-mistakes-were-made-bly-vs-beastyqt/",
      "originalUrl": "https://youtube.com/watch?v=gaBWTfu0Glc",
      "featuredContent": "<iframe width=\"800\" height=\"500\" frameborder=\"0\" src=\"https://www.youtube.com/embed/gaBWTfu0Glc\" allow=\"accelerometer; autoplay; encrypted-media; gyroscope; picture-in-picture\" allowfullscreen></iframe>",
      "length": "PT44M36S",
      "provider": {
        "name": "LowkoTV",
        "domain": "lowko.tv",
        "images": [
          {
            "url": "https://everyday-cc.github.io/starcraft2/assets/images/organizations/lowko.tv-50x50.jpg",
            "width": 50,
            "height": 50,
            "isCached": false
          }
        ]
      },
      "topics": [
        "StarCraft 2"
      ],
      "heat": 52,
      "images": [
        {
          "url": "https://i.ytimg.com/vi/gaBWTfu0Glc/maxresdefault.jpg",
          "width": 1280,
          "height": 720,
          "isCached": true
        }
      ],
      "content": "\r\n",
      "type": "video",
      "publishedDateTime": "2020-10-19T03:09:33-07:00"
    },
    {
      "path": "_games/lowkotv-starcraft-2-neeb-vs-reynor-best-of-5.md",
      "title": "StarCraft 2: NEEB vs REYNOR! (Best-of-5)",
      "excerpt": "Best of 5 series of high level StarCraft 2 between Reynor and Neeb with some fun strategies.  Support my work on Patreon: http://www.patreon.com/lowkotv Become a YouTube member: https://lowko.tv/join  My second channel: http://lowko.tv/morelowko Lowko Merch: http://lowko.tv/merch  Be part of the community",
      "sourceUrl": "https://everyday-cc.github.io/starcraft2/api/games/lowkotv-starcraft-2-neeb-vs-reynor-best-of-5/index.json",
      "webUrl": "https://everyday.cc/starcraft2/game/lowkotv-starcraft-2-neeb-vs-reynor-best-of-5/",
      "originalUrl": "https://youtube.com/watch?v=-W21W1MlUgA",
      "featuredContent": "<iframe width=\"800\" height=\"500\" frameborder=\"0\" src=\"https://www.youtube.com/embed/-W21W1MlUgA\" allow=\"accelerometer; autoplay; encrypted-media; gyroscope; picture-in-picture\" allowfullscreen></iframe>",
      "length": "PT1H6M46S",
      "provider": {
        "name": "LowkoTV",
        "domain": "lowko.tv",
        "images": [
          {
            "url": "https://everyday-cc.github.io/starcraft2/assets/images/organizations/lowko.tv-50x50.jpg",
            "width": 50,
            "height": 50,
            "isCached": false
          }
        ]
      },
      "topics": [
        "StarCraft 2",
        "Protoss",
        "Zerg"
      ],
      "heat": 52,
      "images": [
        {
          "url": "https://i.ytimg.com/vi/-W21W1MlUgA/maxresdefault.jpg",
          "width": 1280,
          "height": 720,
          "isCached": true
        }
      ],
      "content": "\r\n",
      "type": "video",
      "publishedDateTime": "2021-02-17T04:39:22-08:00"
    },
    {
      "path": "_games/lowkotv-starcraft-2-new-maps-scarlett-vs-byun-best-of-3.md",
      "title": "StarCraft 2: NEW MAPS - Scarlett vs ByuN! (Best-of-3)",
      "excerpt": "Best-of-3 series of professional StarCraft 2 between Scarlett (Zerg) versus ByuN (Terran). These games are played on the new maps that were recently announced for SC2.  Support my work on Patreon: https://www.patreon.com/lowkotv Become a YouTube member: https://lowko.tv/join  More Lowko: https://youtube.com/morelowko",
      "sourceUrl": "https://everyday-cc.github.io/starcraft2/api/games/lowkotv-starcraft-2-new-maps-scarlett-vs-byun-best-of-3/index.json",
      "webUrl": "https://everyday.cc/starcraft2/game/lowkotv-starcraft-2-new-maps-scarlett-vs-byun-best-of-3/",
      "originalUrl": "https://youtube.com/watch?v=idETJODPt-A",
      "featuredContent": "<iframe width=\"800\" height=\"500\" frameborder=\"0\" src=\"https://www.youtube.com/embed/idETJODPt-A\" allow=\"accelerometer; autoplay; encrypted-media; gyroscope; picture-in-picture\" allowfullscreen></iframe>",
      "length": "PT26M37S",
      "provider": {
        "name": "LowkoTV",
        "domain": "lowko.tv",
        "images": [
          {
            "url": "https://everyday-cc.github.io/starcraft2/assets/images/organizations/lowko.tv-50x50.jpg",
            "width": 50,
            "height": 50,
            "isCached": false
          }
        ]
      },
      "topics": [
        "StarCraft 2",
        "Terran",
        "Zerg"
      ],
      "heat": 52,
      "images": [
        {
          "url": "https://www.youtube.com/img/desktop/supported_browsers/dinosaur.png",
          "width": 1200,
          "height": 800,
          "isCached": true
        }
      ],
      "content": "\r\n",
      "type": "video",
      "publishedDateTime": "2022-06-24T02:48:55-07:00"
    },
    {
      "path": "_games/lowkotv-starcraft-2-new-patch-is-live-zerg-vs-protoss-is-good-hero-vs-rogue.md",
      "title": "StarCraft 2: NEW PATCH IS LIVE - Zerg vs Protoss is GOOD?! (herO vs Rogue)",
      "excerpt": "The new multiplayer balance patch is finally live in StarCraft 2. In this best-of-5 series I cast a Zerg versus Protoss between herO and Rogue. The new patch primarily addresses this ZvP matchup, nerfing Shield Batteries, Dark Templar, Queens, Lurkers, Void Rays and buffing the Nydus Worm slightly.",
      "sourceUrl": "https://everyday-cc.github.io/starcraft2/api/games/lowkotv-starcraft-2-new-patch-is-live-zerg-vs-protoss-is-good-hero-vs-rogue/index.json",
      "webUrl": "https://everyday.cc/starcraft2/game/lowkotv-starcraft-2-new-patch-is-live-zerg-vs-protoss-is-good-hero-vs-rogue/",
      "originalUrl": "https://youtube.com/watch?v=MPrpq-p0EM8",
      "featuredContent": "<iframe width=\"800\" height=\"500\" frameborder=\"0\" src=\"https://www.youtube.com/embed/MPrpq-p0EM8\" allow=\"accelerometer; autoplay; encrypted-media; gyroscope; picture-in-picture\" allowfullscreen></iframe>",
      "length": "PT44M4S",
      "provider": {
        "name": "LowkoTV",
        "domain": "lowko.tv",
        "images": [
          {
            "url": "https://everyday-cc.github.io/starcraft2/assets/images/organizations/lowko.tv-50x50.jpg",
            "width": 50,
            "height": 50,
            "isCached": false
          }
        ]
      },
      "topics": [
        "StarCraft 2",
        "Protoss",
        "Zerg"
      ],
      "heat": 52,
      "images": [
        {
          "url": "https://www.youtube.com/img/desktop/supported_browsers/dinosaur.png",
          "width": 1200,
          "height": 800,
          "isCached": true
        }
      ],
      "content": "\r\n",
      "type": "video",
      "publishedDateTime": "2022-03-21T05:40:18-07:00"
    },
    {
      "path": "_games/lowkotv-starcraft-2-planetary-problems-florencio.md",
      "title": "StarCraft 2: PLANETARY PROBLEMS! (Florencio)",
      "excerpt": "Fun game of Terran versus Zerg in StarCraft 2 submited by Florencio. Florencio decides to go for an aggressive Planetary Fortress rush.  Florencio on Twitch: http://twitch.tv/florenciosc  Get more videos & support my work: http://www.patreon.com/lowkotv  My second channel: http://lowko.tv/morelowko Lowko",
      "sourceUrl": "https://everyday-cc.github.io/starcraft2/api/games/lowkotv-starcraft-2-planetary-problems-florencio/index.json",
      "webUrl": "https://everyday.cc/starcraft2/game/lowkotv-starcraft-2-planetary-problems-florencio/",
      "originalUrl": "https://youtube.com/watch?v=SOyIjRfiqDg",
      "featuredContent": "<iframe width=\"800\" height=\"500\" frameborder=\"0\" src=\"https://www.youtube.com/embed/SOyIjRfiqDg\" allow=\"accelerometer; autoplay; encrypted-media; gyroscope; picture-in-picture\" allowfullscreen></iframe>",
      "length": "PT26M59S",
      "provider": {
        "name": "LowkoTV",
        "domain": "lowko.tv",
        "images": [
          {
            "url": "https://everyday-cc.github.io/starcraft2/assets/images/organizations/lowko.tv-50x50.jpg",
            "width": 50,
            "height": 50,
            "isCached": false
          }
        ]
      },
      "topics": [
        "StarCraft 2",
        "Terran"
      ],
      "heat": 52,
      "images": [
        {
          "url": "https://i.ytimg.com/vi/SOyIjRfiqDg/maxresdefault.jpg",
          "width": 1280,
          "height": 720,
          "isCached": true
        }
      ],
      "content": "\r\n",
      "type": "video",
      "publishedDateTime": "2020-08-18T11:25:36-07:00"
    },
    {
      "path": "_games/lowkotv-starcraft-2-professional-2v2-team-game.md",
      "title": "StarCraft 2: PROFESSIONAL 2V2! (Team Game)",
      "excerpt": "Cure and Trap vs uThermal and Elazer in 2v2 in StarCraft 2! Subscribe for more videos: http://lowko.tv/youtube Epic archon match: https://goo.gl/echvbd  Not something I usually get to cast! In this video I give commentary to a professional team game in StarCraft 2.  Check out Lowko merchandise: http://lowko.tv/merch",
      "sourceUrl": "https://everyday-cc.github.io/starcraft2/api/games/lowkotv-starcraft-2-professional-2v2-team-game/index.json",
      "webUrl": "https://everyday.cc/starcraft2/game/lowkotv-starcraft-2-professional-2v2-team-game/",
      "originalUrl": "https://youtube.com/watch?v=QJM7wa9N7-4",
      "featuredContent": "<iframe width=\"800\" height=\"500\" frameborder=\"0\" src=\"https://www.youtube.com/embed/QJM7wa9N7-4\" allow=\"accelerometer; autoplay; encrypted-media; gyroscope; picture-in-picture\" allowfullscreen></iframe>",
      "length": "PT18M29S",
      "provider": {
        "name": "LowkoTV",
        "domain": "lowko.tv",
        "images": [
          {
            "url": "https://everyday-cc.github.io/starcraft2/assets/images/organizations/lowko.tv-50x50.jpg",
            "width": 50,
            "height": 50,
            "isCached": false
          }
        ]
      },
      "topics": [
        "StarCraft 2"
      ],
      "heat": 52,
      "images": [
        {
          "url": "https://i.ytimg.com/vi/QJM7wa9N7-4/maxresdefault.jpg",
          "width": 1280,
          "height": 720,
          "isCached": true
        }
      ],
      "content": "\r\n",
      "type": "video",
      "publishedDateTime": "2019-01-14T04:10:23-08:00"
    },
    {
      "path": "_games/lowkotv-starcraft-2-rexs-zergling-rush-vs-hero-best-of-3.md",
      "title": "StarCraft 2: Rex's ZERGLING RUSH vs herO! (Best-of-3)",
      "excerpt": "Best-of-3 series between Rex (Zerg) and herO (Protoss). In this series Rex decides to play an aggressive set of games against the highest ranked Protoss in the world.  Support my work on Patreon: https://www.patreon.com/lowkotv Become a YouTube member: https://lowko.tv/join  More Lowko: https://youtube.com/morelowko",
      "sourceUrl": "https://everyday-cc.github.io/starcraft2/api/games/lowkotv-starcraft-2-rexs-zergling-rush-vs-hero-best-of-3/index.json",
      "webUrl": "https://everyday.cc/starcraft2/game/lowkotv-starcraft-2-rexs-zergling-rush-vs-hero-best-of-3/",
      "originalUrl": "https://youtube.com/watch?v=hbmBk8J8T5Q",
      "featuredContent": "<iframe width=\"800\" height=\"500\" frameborder=\"0\" src=\"https://www.youtube.com/embed/hbmBk8J8T5Q\" allow=\"accelerometer; autoplay; encrypted-media; gyroscope; picture-in-picture\" allowfullscreen></iframe>",
      "length": "PT26M52S",
      "provider": {
        "name": "LowkoTV",
        "domain": "lowko.tv",
        "images": [
          {
            "url": "https://everyday-cc.github.io/starcraft2/assets/images/organizations/lowko.tv-50x50.jpg",
            "width": 50,
            "height": 50,
            "isCached": false
          }
        ]
      },
      "topics": [
        "StarCraft 2",
        "Protoss",
        "Zerg"
      ],
      "heat": 52,
      "images": [
        {
          "url": "https://www.youtube.com/img/desktop/supported_browsers/dinosaur.png",
          "width": 1200,
          "height": 800,
          "isCached": true
        }
      ],
      "content": "\r\n",
      "type": "video",
      "publishedDateTime": "2022-07-11T02:55:05-07:00"
    },
    {
      "path": "_games/lowkotv-starcraft-2-scarlett-vs-neeb-best-of-5.md",
      "title": "StarCraft 2: SCARLETT VS NEEB! (Best-of-5)",
      "excerpt": "Scarlett versus Neeb in a best-of-5 series of StarCraft 2.   Serral vs Maru: https://youtu.be/h4A8ZTaPBAE  Become a YouTube member: https://lowko.tv/join Support my work on Patreon: http://www.patreon.com/lowkotv  My second channel: http://lowko.tv/morelowko Lowko Merch: http://lowko.tv/merch  Be part",
      "sourceUrl": "https://everyday-cc.github.io/starcraft2/api/games/lowkotv-starcraft-2-scarlett-vs-neeb-best-of-5/index.json",
      "webUrl": "https://everyday.cc/starcraft2/game/lowkotv-starcraft-2-scarlett-vs-neeb-best-of-5/",
      "originalUrl": "https://youtube.com/watch?v=yPXkXTRZgYw",
      "featuredContent": "<iframe width=\"800\" height=\"500\" frameborder=\"0\" src=\"https://www.youtube.com/embed/yPXkXTRZgYw\" allow=\"accelerometer; autoplay; encrypted-media; gyroscope; picture-in-picture\" allowfullscreen></iframe>",
      "length": "PT49M6S",
      "provider": {
        "name": "LowkoTV",
        "domain": "lowko.tv",
        "images": [
          {
            "url": "https://everyday-cc.github.io/starcraft2/assets/images/organizations/lowko.tv-50x50.jpg",
            "width": 50,
            "height": 50,
            "isCached": false
          }
        ]
      },
      "topics": [
        "StarCraft 2",
        "Protoss",
        "Zerg"
      ],
      "heat": 52,
      "images": [
        {
          "url": "https://i.ytimg.com/vi/yPXkXTRZgYw/maxresdefault.jpg",
          "width": 1280,
          "height": 720,
          "isCached": true
        }
      ],
      "content": "\r\n",
      "type": "video",
      "publishedDateTime": "2020-10-09T03:45:25-07:00"
    },
    {
      "path": "_games/lowkotv-starcraft-2-scarletts-protoss-offrace-scarlett-vs-pig.md",
      "title": "StarCraft 2: Scarlett's PROTOSS Offrace?! (Scarlett vs PiG)",
      "excerpt": "This game of StarCraft 2 is from a recent ESL Open Cup. In this match we watch Scarlett pick up the Protoss pieces versus PiG who plays as Zerg. Scarlett normally plays Zerg, but decides to focus on a macro game with Protoss. PiG rushes up to Hive tech with Ultralisks and deals a ton of damage while",
      "sourceUrl": "https://everyday-cc.github.io/starcraft2/api/games/lowkotv-starcraft-2-scarletts-protoss-offrace-scarlett-vs-pig/index.json",
      "webUrl": "https://everyday.cc/starcraft2/game/lowkotv-starcraft-2-scarletts-protoss-offrace-scarlett-vs-pig/",
      "originalUrl": "https://youtube.com/watch?v=oRE7QFqsefc",
      "featuredContent": "<iframe width=\"800\" height=\"500\" frameborder=\"0\" src=\"https://www.youtube.com/embed/oRE7QFqsefc\" allow=\"accelerometer; autoplay; encrypted-media; gyroscope; picture-in-picture\" allowfullscreen></iframe>",
      "length": "PT21M57S",
      "provider": {
        "name": "LowkoTV",
        "domain": "lowko.tv",
        "images": [
          {
            "url": "https://everyday-cc.github.io/starcraft2/assets/images/organizations/lowko.tv-50x50.jpg",
            "width": 50,
            "height": 50,
            "isCached": false
          }
        ]
      },
      "topics": [
        "StarCraft 2",
        "Protoss",
        "Zerg"
      ],
      "heat": 52,
      "images": [
        {
          "url": "https://www.youtube.com/img/desktop/supported_browsers/dinosaur.png",
          "width": 1200,
          "height": 800,
          "isCached": true
        }
      ],
      "content": "\r\n",
      "type": "video",
      "publishedDateTime": "2022-04-22T05:00:57-07:00"
    },
    {
      "path": "_games/lowkotv-starcraft-2-serrals-swarm-hosts-vs-dreams-mech-best-of-3.md",
      "title": "StarCraft 2: Serral's SWARM HOSTS vs Dream's MECH! (Best-of-3)",
      "excerpt": "Best-of-3 series of professional StarCraft 2 between Serral (Zerg) and Dream (Terran). While Serral is favoured in this Zerg versus Terran, Dream has some tricky build orders.  Support my work on Patreon: https://www.patreon.com/lowkotv Become a YouTube member: https://lowko.tv/join  More Lowko: https://youtube.com/morelowko",
      "sourceUrl": "https://everyday-cc.github.io/starcraft2/api/games/lowkotv-starcraft-2-serrals-swarm-hosts-vs-dreams-mech-best-of-3/index.json",
      "webUrl": "https://everyday.cc/starcraft2/game/lowkotv-starcraft-2-serrals-swarm-hosts-vs-dreams-mech-best-of-3/",
      "originalUrl": "https://youtube.com/watch?v=7TLtdZVLb6s",
      "featuredContent": "<iframe width=\"800\" height=\"500\" frameborder=\"0\" src=\"https://www.youtube.com/embed/7TLtdZVLb6s\" allow=\"accelerometer; autoplay; encrypted-media; gyroscope; picture-in-picture\" allowfullscreen></iframe>",
      "length": "PT36M41S",
      "provider": {
        "name": "LowkoTV",
        "domain": "lowko.tv",
        "images": [
          {
            "url": "https://everyday-cc.github.io/starcraft2/assets/images/organizations/lowko.tv-50x50.jpg",
            "width": 50,
            "height": 50,
            "isCached": false
          }
        ]
      },
      "topics": [
        "StarCraft 2",
        "Zerg"
      ],
      "heat": 52,
      "images": [
        {
          "url": "https://i.ytimg.com/vi/7TLtdZVLb6s/maxresdefault.jpg",
          "width": 1280,
          "height": 720,
          "isCached": true
        }
      ],
      "content": "\r\n",
      "type": "video",
      "publishedDateTime": "2022-01-28T04:33:03-08:00"
    },
    {
      "path": "_games/lowkotv-starcraft-2-solars-proxy-spine-crawler-vs-reynor-best-of-5.md",
      "title": "StarCraft 2: Solar's PROXY SPINE CRAWLER vs Reynor! (Best-of-5)",
      "excerpt": "Best-of-5 series of top level professional StarCraft 2 between Solar and Reynor. In this Zerg versus Zerg a variety of cheeses are played, as well as solid macro.  Support my work on Patreon: https://www.patreon.com/lowkotv Become a YouTube member: https://lowko.tv/join  My second channel: https://youtube.com/morelowko",
      "sourceUrl": "https://everyday-cc.github.io/starcraft2/api/games/lowkotv-starcraft-2-solars-proxy-spine-crawler-vs-reynor-best-of-5/index.json",
      "webUrl": "https://everyday.cc/starcraft2/game/lowkotv-starcraft-2-solars-proxy-spine-crawler-vs-reynor-best-of-5/",
      "originalUrl": "https://youtube.com/watch?v=yzNvWWEO710",
      "featuredContent": "<iframe width=\"800\" height=\"500\" frameborder=\"0\" src=\"https://www.youtube.com/embed/yzNvWWEO710\" allow=\"accelerometer; autoplay; encrypted-media; gyroscope; picture-in-picture\" allowfullscreen></iframe>",
      "length": "PT42M56S",
      "provider": {
        "name": "LowkoTV",
        "domain": "lowko.tv",
        "images": [
          {
            "url": "https://everyday-cc.github.io/starcraft2/assets/images/organizations/lowko.tv-50x50.jpg",
            "width": 50,
            "height": 50,
            "isCached": false
          }
        ]
      },
      "topics": [
        "StarCraft 2",
        "Zerg"
      ],
      "heat": 52,
      "images": [
        {
          "url": "https://i.ytimg.com/vi/yzNvWWEO710/maxresdefault.jpg",
          "width": 1280,
          "height": 720,
          "isCached": true
        }
      ],
      "content": "\r\n",
      "type": "video",
      "publishedDateTime": "2022-01-24T04:08:31-08:00"
    },
    {
      "path": "_games/lowkotv-starcraft-2-still-planetary-fortress-rushing-in-2022-viewer-games.md",
      "title": "StarCraft 2: Still PLANETARY FORTRESS RUSHING in 2022…? (Viewer Games)",
      "excerpt": "Two games of StarCraft 2 submitted to me by viewers. If you want to me make fun of your SC2 games as well, make sure to send your best replays to replays@lowko.tv.  Support my work on Patreon: https://www.patreon.com/lowkotv Become a YouTube member: https://lowko.tv/join  More Lowko: https://youtube.com/morelowko",
      "sourceUrl": "https://everyday-cc.github.io/starcraft2/api/games/lowkotv-starcraft-2-still-planetary-fortress-rushing-in-2022-viewer-games/index.json",
      "webUrl": "https://everyday.cc/starcraft2/game/lowkotv-starcraft-2-still-planetary-fortress-rushing-in-2022-viewer-games/",
      "originalUrl": "https://youtube.com/watch?v=W6LVBNdjwkk",
      "featuredContent": "<iframe width=\"800\" height=\"500\" frameborder=\"0\" src=\"https://www.youtube.com/embed/W6LVBNdjwkk\" allow=\"accelerometer; autoplay; encrypted-media; gyroscope; picture-in-picture\" allowfullscreen></iframe>",
      "length": "PT30M18S",
      "provider": {
        "name": "LowkoTV",
        "domain": "lowko.tv",
        "images": [
          {
            "url": "https://everyday-cc.github.io/starcraft2/assets/images/organizations/lowko.tv-50x50.jpg",
            "width": 50,
            "height": 50,
            "isCached": false
          }
        ]
      },
      "topics": [
        "StarCraft 2",
        "Terran"
      ],
      "heat": 52,
      "images": [
        {
          "url": "https://www.youtube.com/img/desktop/supported_browsers/dinosaur.png",
          "width": 1200,
          "height": 800,
          "isCached": true
        }
      ],
      "content": "\r\n",
      "type": "video",
      "publishedDateTime": "2022-02-14T02:35:43-08:00"
    }
  ],
  "nextPage": 13
}